Compiled from "HelloBytecode.java"
public class HelloBytecode {
  public HelloBytecode();
    Code:
       0: aload_0
       1: invokespecial #1                  
       4: return

  public int square(int);
    Code:
       0: iload_1
       1: iload_1
       2: imul
       3: ireturn

  public static void main(java.lang.String[]);
    Code:
       0: new           #2                  
       3: dup
       4: invokespecial #3                  
       7: astore_1
       8: getstatic     #4                  
      11: aload_1
      12: iconst_5
      13: invokevirtual #5                   
      16: invokevirtual #6                  
      19: return
}

